labelstream/labelstream.py
labelstream-0.0.1.dist-info/METADATA
labelstream-0.0.1.dist-info/WHEEL
labelstream-0.0.1.dist-info/entry_points.txt
labelstream-0.0.1.dist-info/top_level.txt
labelstream-0.0.1.dist-info/RECORD
