Metadata-Version: 2.1
Name: labelstream
Version: 0.0.1
Summary: UNKNOWN
Home-page: UNKNOWN
License: UNKNOWN
Platform: UNKNOWN
Requires-Python: >=3.8
Requires-Dist: click
Provides-Extra: dev
Requires-Dist: jupyter ; extra == 'dev'
